scanflow/__init__.py
scanflow/_version.py
scanflow/agent/__init__.py
scanflow/agent/agent_router.py
scanflow/agent/main.py
scanflow/agent/config/__init__.py
scanflow/agent/config/httpClient.py
scanflow/agent/config/settings.py
scanflow/agent/schemas/__init__.py
scanflow/agent/schemas/message.py
scanflow/agent/schemas/requestData.py
scanflow/agent/schemas/sensor.py
scanflow/agent/sensors/__init__.py
scanflow/agent/sensors/sensor.py
scanflow/agent/sensors/sensor_dependency.py
scanflow/agent/sensors/sensors.py
scanflow/agent/sensors/sensors_trigger.py
scanflow/app/__init__.py
scanflow/app/application.py
scanflow/app/scanflowTracker.py
scanflow/app/utils.py
scanflow/app/agent/__init__.py
scanflow/app/agent/agent.py
scanflow/app/agent/sensor.py
scanflow/app/workflow/__init__.py
scanflow/app/workflow/edge.py
scanflow/app/workflow/node.py
scanflow/app/workflow/scaler.py
scanflow/app/workflow/workflow.py
scanflow/builder/__init__.py
scanflow/builder/builder.py
scanflow/builder/dockerBuilder.py
scanflow/client/__init__.py
scanflow/client/httpClient.py
scanflow/client/scanflowClient.py
scanflow/client/scanflowDeployerClient.py
scanflow/client/scanflowTrackerClient.py
scanflow/deployer/__init__.py
scanflow/deployer/argoDeployer.py
scanflow/deployer/deployer.py
scanflow/deployer/seldonDeployer.py
scanflow/deployer/utils.py
scanflow/deployer/volcanoDeployer.py
scanflow/deployer/env/__init__.py
scanflow/deployer/env/env.py
scanflow/graph/__init__.py
scanflow/graph/agentsGraph.py
scanflow/graph/applicationGraph.py
scanflow/graph/scanflowGraph.py
scanflow/graph/workflowsGraph.py
scanflow/server/__init__.py
scanflow/server/dependencies.py
scanflow/server/server.py
scanflow/server/utils.py
scanflow/server/routers/__init__.py
scanflow/server/routers/scanflowApplication.py
scanflow/server/routers/scanflowDeployer.py
scanflow/server/routers/scanflowModel.py
scanflow/templates/__init__.py
scanflow/templates/argoWorkflows.py
scanflow/templates/kubernetes.py
scanflow-0.1.1.dist-info/LICENSE
scanflow-0.1.1.dist-info/METADATA
scanflow-0.1.1.dist-info/WHEEL
scanflow-0.1.1.dist-info/top_level.txt
scanflow-0.1.1.dist-info/RECORD
